{
  "posts": [
    { "id": 1, "title": "Post 1" },
    { "id": 2, "title": "Post 2" },
    { "id": 3, "title": "Post 3" }
  ],
  "comments": [
    { "id": 1, "body": "some comment", "postId": 1 },
    { "id": 2, "body": "some comment", "postId": 1 }
  ],
  "profile": {
    "name": "typicode"
  },
      "Data":{
        "data":[
                    {
                        "year":"2013",
                        "number":31369,
                        "s":"1"
                    },
                    {
                        "year":"2014",
                        "number":32453,
                        "s":"1"
                    },
                    {
                        "year":"2015",
                        "number":33500,
                        "s":"1"
                    },
                    {
                        "year":"2016",
                        "number":59470,
                        "s":"1"
                    },
                    {
                        "year":"2017",
                        "number":16377,
                        "s":"1"
                    },
                    {
                        "year":"2018",
                        "number":29089,
                        "s":"1"
                    },
                    {
                        "year":"2013",
                        "number":11161,
                        "s":"2"
                    }
                ]
             }
}
